Data/IOTDataProcessor.py
Data/IOTDataStructure.py
Data/__init__.py
Model/IOTModelGenerator.py
Model/__init__.py
IOTLibrary-0.0.0.0.dist-info/METADATA
IOTLibrary-0.0.0.0.dist-info/WHEEL
IOTLibrary-0.0.0.0.dist-info/top_level.txt
IOTLibrary-0.0.0.0.dist-info/RECORD
