Metadata-Version: 2.1
Name: IOTLibrary
Version: 0.0.0.0
Summary: IOTAILibrary
Home-page: https://github.com/HuangTeEn
Author: TimmyHuang
Author-email: timmy.huang.iot@gmail.com
License: UNKNOWN
Platform: UNKNOWN
Classifier: Programming Language :: Python :: 3
Classifier: License :: OSI Approved :: MIT License
Classifier: Operating System :: OS Independent
Requires-Python: >=3.6
